{
    "swagger": "2.0",
    "info": {
        "description": "Time Tracker Api",
        "title": "Time Tracker Api",
        "contact": {
            "name": "Bogdan Lupu",
            "email": "lupu60@gmail.com"
        },
        "version": "1.0"
    },
    "host": "https://api.time-tracker.ml/",
    "basePath": "/api/",
    "paths": {
        "/clients": {
            "get": {
                "produces": [
                    "application/json"
                ],
                "tags": [
                    "clients"
                ],
                "responses": {
                    "200": {
                        "description": ""
                    }
                }
            },
            "post": {
                "consumes": [
                    "application/json"
                ],
                "produces": [
                    "application/json"
                ],
                "tags": [
                    "clients"
                ],
                "parameters": [
                    {
                        "description": "Client",
                        "name": "client",
                        "in": "body",
                        "required": true,
                        "schema": {
                            "$ref": "#/definitions/clients.Client"
                        }
                    }
                ],
                "responses": {
                    "200": {
                        "description": ""
                    }
                }
            }
        },
        "/clients/:id": {
            "get": {
                "produces": [
                    "application/json"
                ],
                "tags": [
                    "clients"
                ],
                "parameters": [
                    {
                        "type": "string",
                        "description": "Clients ID",
                        "name": "id",
                        "in": "path",
                        "required": true
                    }
                ],
                "responses": {
                    "200": {
                        "description": ""
                    }
                }
            },
            "delete": {
                "produces": [
                    "application/json"
                ],
                "tags": [
                    "clients"
                ],
                "parameters": [
                    {
                        "type": "string",
                        "description": "Client ID",
                        "name": "id",
                        "in": "path",
                        "required": true
                    }
                ],
                "responses": {
                    "200": {
                        "description": ""
                    }
                }
            }
        },
        "/login": {
            "post": {
                "produces": [
                    "application/json"
                ],
                "tags": [
                    "auth"
                ],
                "parameters": [
                    {
                        "description": "auth",
                        "name": "login",
                        "in": "body",
                        "required": true,
                        "schema": {
                            "$ref": "#/definitions/auth.LoginDTO"
                        }
                    }
                ],
                "responses": {
                    "200": {
                        "description": ""
                    }
                }
            }
        },
        "/register": {
            "post": {
                "produces": [
                    "application/json"
                ],
                "tags": [
                    "auth"
                ],
                "parameters": [
                    {
                        "description": "User",
                        "name": "user",
                        "in": "body",
                        "required": true,
                        "schema": {
                            "$ref": "#/definitions/users.User"
                        }
                    }
                ],
                "responses": {
                    "200": {
                        "description": ""
                    }
                }
            }
        },
        "/users": {
            "get": {
                "produces": [
                    "application/json"
                ],
                "tags": [
                    "users"
                ],
                "responses": {
                    "200": {
                        "description": ""
                    }
                }
            },
            "post": {
                "consumes": [
                    "application/json"
                ],
                "produces": [
                    "application/json"
                ],
                "tags": [
                    "users"
                ],
                "parameters": [
                    {
                        "description": "User",
                        "name": "user",
                        "in": "body",
                        "required": true,
                        "schema": {
                            "$ref": "#/definitions/users.User"
                        }
                    }
                ],
                "responses": {
                    "200": {
                        "description": ""
                    }
                }
            }
        },
        "/users/:id": {
            "get": {
                "produces": [
                    "application/json"
                ],
                "tags": [
                    "users"
                ],
                "parameters": [
                    {
                        "type": "string",
                        "description": "User ID",
                        "name": "id",
                        "in": "path",
                        "required": true
                    }
                ],
                "responses": {
                    "200": {
                        "description": ""
                    }
                }
            },
            "delete": {
                "produces": [
                    "application/json"
                ],
                "tags": [
                    "users"
                ],
                "parameters": [
                    {
                        "type": "string",
                        "description": "User ID",
                        "name": "id",
                        "in": "path",
                        "required": true
                    }
                ],
                "responses": {
                    "200": {
                        "description": ""
                    }
                }
            }
        },
        "/users/:id/projects": {
            "post": {
                "produces": [
                    "application/json"
                ],
                "tags": [
                    "users"
                ],
                "responses": {
                    "200": {
                        "description": ""
                    }
                }
            }
        },
        "/users/:id/worklog": {
            "get": {
                "produces": [
                    "application/json"
                ],
                "tags": [
                    "users"
                ],
                "responses": {
                    "200": {
                        "description": ""
                    }
                }
            },
            "post": {
                "produces": [
                    "application/json"
                ],
                "tags": [
                    "users"
                ],
                "parameters": [
                    {
                        "description": "worklog",
                        "name": "worklog",
                        "in": "body",
                        "required": true,
                        "schema": {
                            "$ref": "#/definitions/users.Worklog"
                        }
                    }
                ],
                "responses": {
                    "200": {
                        "description": ""
                    }
                }
            }
        }
    },
    "definitions": {
        "auth.LoginDTO": {
            "type": "object",
            "required": [
                "email",
                "password"
            ],
            "properties": {
                "email": {
                    "type": "string"
                },
                "password": {
                    "type": "string"
                }
            }
        },
        "clients.Client": {
            "type": "object",
            "properties": {
                "created_at": {
                    "type": "string"
                },
                "id": {
                    "type": "string"
                },
                "name": {
                    "type": "string"
                },
                "projects": {
                    "type": "array",
                    "items": {
                        "$ref": "#/definitions/clients.Project"
                    }
                },
                "updated_at": {
                    "type": "string"
                }
            }
        },
        "clients.Project": {
            "type": "object",
            "properties": {
                "created_at": {
                    "type": "string"
                },
                "id": {
                    "type": "string"
                },
                "name": {
                    "type": "string"
                },
                "updated_at": {
                    "type": "string"
                }
            }
        },
        "users.User": {
            "type": "object",
            "properties": {
                "created_at": {
                    "type": "string"
                },
                "email": {
                    "type": "string"
                },
                "first_name": {
                    "type": "string"
                },
                "id": {
                    "type": "string"
                },
                "password": {
                    "type": "string"
                },
                "projects": {
                    "type": "array",
                    "items": {
                        "$ref": "#/definitions/clients.Project"
                    }
                },
                "updated_at": {
                    "type": "string"
                },
                "user_name": {
                    "type": "string"
                }
            }
        },
        "users.Worklog": {
            "type": "object",
            "properties": {
                "description": {
                    "type": "string"
                },
                "hours": {
                    "type": "integer"
                },
                "id": {
                    "type": "string"
                },
                "project_id": {
                    "type": "string"
                }
            }
        }
    },
    "securityDefinitions": {
        "Bearer": {
            "type": "apiKey",
            "name": "Authorization",
            "in": "header"
        }
    }
}